logger/__init__.py
logger/log.ini
logger/logger.py
twnlog/__init__.py
twnlog/log.ini
twnlog/logger.py
twnlog-0.2.0.dist-info/LICENSE
twnlog-0.2.0.dist-info/METADATA
twnlog-0.2.0.dist-info/WHEEL
twnlog-0.2.0.dist-info/top_level.txt
twnlog-0.2.0.dist-info/RECORD
