Metadata-Version: 2.1
Name: twnlog
Version: 0.2.0
Summary: 自定义LOG模块
Home-page: UNKNOWN
Author: bennett
Author-email: 1342183835@qq.com
License: GNU GPLv3 Licence
Platform: any
Requires-Python: >=3.6.0
Requires-Dist: loguru
Requires-Dist: pathlib
